{
  "project_info": {
    "project_number": "1043837451985",
    "project_id": "mybooks-9b008",
    "storage_bucket": "mybooks-9b008.appspot.com"
  },
  "client": [
    {
      "client_info": {
        "mobilesdk_app_id": "1:1043837451985:android:c9fa0d8109887d0f1c0ff0",
        "android_client_info": {
          "package_name": "com.mybooks"
        }
      },
      "oauth_client": [
        {
          "client_id": "1043837451985-kpga2qr7rfracc93k7820m8kfj8ac1t8.apps.googleusercontent.com",
          "client_type": 3
        }
      ],
      "api_key": [
        {
          "current_key": "AIzaSyCAj8jdId5utqMg5Plk2AKgmQUS8s5h3T4"
        }
      ],
      "services": {
        "appinvite_service": {
          "other_platform_oauth_client": [
            {
              "client_id": "1043837451985-kpga2qr7rfracc93k7820m8kfj8ac1t8.apps.googleusercontent.com",
              "client_type": 3
            }
          ]
        }
      }
    }
  ],
  "configuration_version": "1"
}